{"nodes": {"0fedfc0e-24ea-47ea-9ac1-793729cc8848": {"coords": [60, 60, 0], "duration": 0, "requires": [0], "tw": [null, null], "precedes": []}, "7064cc08-cff0-452e-8b8c-1b38e0df0cf9": {"coords": [36, 47, 0], "duration": 119, "requires": [1], "tw": [null, null], "precedes": []}, "be33fff1-ac96-46cb-afcb-6d75a0764392": {"coords": [134, 20, 0], "duration": 36, "requires": [1], "tw": [null, null], "precedes": []}, "7b3a6a58-fadd-4b32-a921-3e0dc81df30c": {"coords": [66, 71, 0], "duration": 36, "requires": [0], "tw": [null, null], "precedes": []}, "82183658-9763-4b14-915b-90f10f55c613": {"coords": [142, 31, 0], "duration": 119, "requires": [0], "tw": [null, null], "precedes": []}, "bc25864f-8e4a-489c-ad25-bd1254afec9c": {"coords": [27, 0, 0], "duration": 36, "requires": [0], "tw": [null, null], "precedes": []}, "3f32bfe9-12c1-484d-9ba6-83ec341ad8cc": {"coords": [14, 52, 0], "duration": 36, "requires": [2], "tw": [null, null], "precedes": []}, "76cd1b08-7782-4cd4-99d8-64d4e870bdf5": {"coords": [102, 80, 0], "duration": 67, "requires": [0], "tw": [null, null], "precedes": []}, "cf33dc0f-0ca5-4b7f-a300-0d30aef544c5": {"coords": [49, 28, 0], "duration": 119, "requires": [0], "tw": [null, null], "precedes": []}, "1b2a467b-76e0-4133-9be8-b2cac84bf29e": {"coords": [35, 3, 0], "duration": 36, "requires": [2], "tw": [null, null], "precedes": []}, "39222bae-a13c-4662-b49d-43d7a95e4760": {"coords": [131, 59, 0], "duration": 36, "requires": [1], "tw": [null, null], "precedes": []}, "bb0ebc60-851d-4325-bc96-5c8cdebea93b": {"coords": [45, 21, 0], "duration": 119, "requires": [1], "tw": [null, null], "precedes": []}, "6251990d-f274-4e7e-96d0-fa7d1fabfb22": {"coords": [148, 25, 0], "duration": 119, "requires": [1], "tw": [null, null], "precedes": []}, "f0de2832-03e2-4d13-9bf1-3c4883711746": {"coords": [33, 43, 0], "duration": 36, "requires": [0], "tw": [null, null], "precedes": []}, "6de8a6b5-87b6-4df9-98e3-5231e660dd3c": {"coords": [116, 65, 0], "duration": 67, "requires": [0], "tw": [null, null], "precedes": []}, "6893ad78-2a57-4924-bef4-b320df2035b8": {"coords": [27, 82, 0], "duration": 67, "requires": [0], "tw": [null, null], "precedes": []}, "06b5845b-46aa-41eb-a25e-5f0fe961b393": {"coords": [111, 28, 0], "duration": 67, "requires": [1], "tw": [null, null], "precedes": []}, "e0c86db9-4cf0-4534-bdd6-9718f9d1ba74": {"coords": [71, 68, 0], "duration": 67, "requires": [2], "tw": [null, null], "precedes": []}, "35f45777-522e-46cf-8cf1-37dee9cae2ce": {"coords": [100, 55, 0], "duration": 67, "requires": [0], "tw": [null, null], "precedes": []}, "4fda6b40-b65b-4a2f-9ee3-f6360698bb22": {"coords": [44, 24, 0], "duration": 119, "requires": [2], "tw": [null, null], "precedes": []}, "acbebe66-3925-4e04-8ee8-f2893ceaa88f": {"coords": [1, 95, 0], "duration": 67, "requires": [0], "tw": [null, null], "precedes": []}, "44957015-86f5-4733-bbc1-b03316737c3c": {"coords": [91, 27, 0], "duration": 67, "requires": [1], "tw": [null, null], "precedes": []}, "7d35f026-7bb5-4784-b61e-6e2e3347f155": {"coords": [78, 46, 0], "duration": 67, "requires": [2], "tw": [null, null], "precedes": []}, "ecac58d0-9e9b-48eb-b346-0b71d450c0f7": {"coords": [6, 79, 0], "duration": 36, "requires": [1], "tw": [null, null], "precedes": []}, "3d151a40-d263-4dea-b4bc-fd2bc3754f16": {"coords": [70, 39, 0], "duration": 67, "requires": [2], "tw": [null, null], "precedes": []}, "7dd511ed-5c8f-4818-bc9f-e9341b0181c7": {"coords": [82, 60, 0], "duration": 119, "requires": [2], "tw": [null, null], "precedes": []}, "c3152486-4c00-47f2-9a8b-6508328b0583": {"coords": [76, 97, 0], "duration": 67, "requires": [1], "tw": [null, null], "precedes": []}, "4731e69c-7ebf-44c5-9918-77d01e797623": {"coords": [82, 98, 0], "duration": 36, "requires": [0], "tw": [null, null], "precedes": []}, "eb35d1fc-fdb9-4122-a322-709241417d85": {"coords": [99, 87, 0], "duration": 67, "requires": [1], "tw": [null, null], "precedes": []}, "8de3747e-7365-472a-a96e-32c43868cc4b": {"coords": [108, 56, 0], "duration": 36, "requires": [1], "tw": [null, null], "precedes": []}, "e82670a0-07c3-4040-8755-f84bc7438b83": {"coords": [56, 3, 0], "duration": 119, "requires": [0], "tw": [null, null], "precedes": []}, "4e90fb5d-92d5-4c43-9fb9-dec3f1ef70de": {"coords": [10, 85, 0], "duration": 67, "requires": [2], "tw": [null, null], "precedes": []}, "fef4a9bd-7127-4b2e-9aa6-27ec18e383eb": {"coords": [21, 60, 0], "duration": 67, "requires": [2], "tw": [null, null], "precedes": []}, "60987b75-218b-4c7e-bb30-c191aed27310": {"coords": [134, 19, 0], "duration": 119, "requires": [2], "tw": [null, null], "precedes": []}, "eccbd70e-6ad8-47ea-8081-ded1d6e24d22": {"coords": [64, 24, 0], "duration": 67, "requires": [0], "tw": [null, null], "precedes": []}, "596bd41d-8b57-4c75-8bd1-4391b3166fe0": {"coords": [113, 52, 0], "duration": 67, "requires": [1], "tw": [null, null], "precedes": []}, "97ed68c6-02c0-43e5-a38c-5ace865c5dc2": {"coords": [10, 3, 0], "duration": 119, "requires": [1], "tw": [null, null], "precedes": []}, "f5488e0a-99d4-41a4-977d-79eae7d60399": {"coords": [52, 16, 0], "duration": 67, "requires": [1], "tw": [null, null], "precedes": []}, "088ed378-af63-44d0-8cf1-c2198e3e24c0": {"coords": [61, 89, 0], "duration": 36, "requires": [1], "tw": [null, null], "precedes": []}, "51542d51-d4a2-4a5b-bfc9-500fe25e3b08": {"coords": [74, 19, 0], "duration": 36, "requires": [1], "tw": [null, null], "precedes": []}, "299675ea-cb40-4ce0-ab80-67926cd849b4": {"coords": [5, 8, 0], "duration": 119, "requires": [2], "tw": [null, null], "precedes": []}, "4cf4a568-2a58-46c6-83dc-a8d910dffca3": {"coords": [42, 44, 0], "duration": 36, "requires": [2], "tw": [null, null], "precedes": []}, "d6636902-f8f5-4015-b696-eb9a3f51e67a": {"coords": [91, 34, 0], "duration": 36, "requires": [0], "tw": [null, null], "precedes": []}, "1855e8a4-2d5b-4089-938e-6525953ca41f": {"coords": [30, 42, 0], "duration": 119, "requires": [2], "tw": [null, null], "precedes": []}, "a0e4fe01-e84b-4fe2-9e9a-6c4e904fdb23": {"coords": [11, 27, 0], "duration": 67, "requires": [2], "tw": [null, null], "precedes": []}, "8411b805-b817-4f9d-ac06-f85b990e336b": {"coords": [140, 51, 0], "duration": 67, "requires": [2], "tw": [null, null], "precedes": []}, "b634d251-4a27-4787-9a92-be96b2aad1d8": {"coords": [33, 88, 0], "duration": 119, "requires": [2], "tw": [null, null], "precedes": []}, "4c770755-c2e7-4497-9402-0a573ddb58c7": {"coords": [87, 73, 0], "duration": 36, "requires": [0], "tw": [null, null], "precedes": []}, "cdac5b3f-7e20-482b-845d-fe267acf3e99": {"coords": [9, 28, 0], "duration": 119, "requires": [0], "tw": [null, null], "precedes": []}, "9fd02fc5-98c8-4caa-94bd-4943ca38037b": {"coords": [23, 21, 0], "duration": 67, "requires": [1], "tw": [null, null], "precedes": []}, "ca30ddc1-e0b8-4c18-a463-dfdc30586307": {"coords": [10, 65, 0], "duration": 119, "requires": [1], "tw": [null, null], "precedes": []}, "07e40b2d-fdff-4979-b3fc-9664304574c6": {"coords": [119, 9, 0], "duration": 119, "requires": [2], "tw": [null, null], "precedes": []}, "92a7ca07-0d3a-40cb-814b-57b4de5abe38": {"coords": [5, 75, 0], "duration": 67, "requires": [1], "tw": [null, null], "precedes": []}, "2e0f0cd7-ccef-4393-b3c8-2a975a2792be": {"coords": [140, 60, 0], "duration": 119, "requires": [2], "tw": [null, null], "precedes": []}, "175db773-da03-4a74-ac44-8c4e04115b14": {"coords": [77, 37, 0], "duration": 119, "requires": [1], "tw": [null, null], "precedes": []}, "3d5a53f1-b165-4993-aef0-b73e2a51c3dd": {"coords": [98, 48, 0], "duration": 119, "requires": [0], "tw": [null, null], "precedes": []}, "de23e45d-5aae-4384-83ab-891d34354a9d": {"coords": [149, 55, 0], "duration": 67, "requires": [2], "tw": [null, null], "precedes": []}, "087d4cbc-928f-45f1-b3d9-b784b03b55b6": {"coords": [138, 9, 0], "duration": 119, "requires": [1], "tw": [null, null], "precedes": []}, "0863361d-46f6-4d1d-8394-332af1bbe70d": {"coords": [19, 6, 0], "duration": 36, "requires": [2], "tw": [null, null], "precedes": []}, "52b23d75-0209-47db-984a-ce044e79bbd8": {"coords": [31, 45, 0], "duration": 119, "requires": [0], "tw": [null, null], "precedes": []}, "29c5b3a8-e9ed-42dd-b1e7-afbe21e678b0": {"coords": [53, 27, 0], "duration": 36, "requires": [2], "tw": [null, null], "precedes": []}, "3c81f076-5ddb-4c3b-803f-d7aad200e487": {"coords": [84, 78, 0], "duration": 67, "requires": [2], "tw": [null, null], "precedes": []}, "12456c5b-2d0e-41b6-8c4b-c9807c80ff0d": {"coords": [131, 8, 0], "duration": 119, "requires": [2], "tw": [null, null], "precedes": []}, "1ebed4e3-e650-4a85-8625-e18480c98e9e": {"coords": [14, 4, 0], "duration": 119, "requires": [1], "tw": [null, null], "precedes": []}, "5b7562d6-b6f2-49ae-aff1-ac2ed282fa08": {"coords": [31, 81, 0], "duration": 36, "requires": [1], "tw": [null, null], "precedes": []}, "acb9ed7d-b82c-4afd-b328-74c69c471d31": {"coords": [72, 45, 0], "duration": 36, "requires": [2], "tw": [null, null], "precedes": []}, "295c75e5-421c-45b4-a818-3f45e6fa3284": {"coords": [103, 80, 0], "duration": 36, "requires": [0], "tw": [null, null], "precedes": []}, "7de36fc4-f2cb-471c-b083-1dec7a1439d3": {"coords": [46, 85, 0], "duration": 67, "requires": [2], "tw": [null, null], "precedes": []}, "0a4acb68-c7d8-46b2-a8d5-d0f65fac3c4a": {"coords": [93, 92, 0], "duration": 36, "requires": [1], "tw": [null, null], "precedes": []}, "1f10c1bf-5c45-454a-81b7-10b8f8bbbd36": {"coords": [136, 40, 0], "duration": 67, "requires": [2], "tw": [null, null], "precedes": []}, "37b43b7d-485a-4ebd-9177-144a8d41060c": {"coords": [122, 13, 0], "duration": 119, "requires": [0], "tw": [null, null], "precedes": []}, "f879034f-bc4a-4e98-b23d-51c97484358a": {"coords": [34, 68, 0], "duration": 119, "requires": [2], "tw": [null, null], "precedes": []}, "478922a7-89fd-476f-9393-c49c19d2c131": {"coords": [117, 29, 0], "duration": 119, "requires": [0], "tw": [null, null], "precedes": []}, "14fae682-e49a-4f92-92b5-743f4f13af84": {"coords": [123, 50, 0], "duration": 119, "requires": [0], "tw": [null, null], "precedes": []}, "f65efab8-2d89-4c76-a64c-9cc43fe054d1": {"coords": [6, 59, 0], "duration": 36, "requires": [1], "tw": [null, null], "precedes": []}, "4dfba69a-b487-4c0e-b066-ce028f4d16bc": {"coords": [28, 29, 0], "duration": 67, "requires": [0], "tw": [null, null], "precedes": []}, "f559d02c-73b2-4703-af5a-befb9497fdbb": {"coords": [80, 51, 0], "duration": 67, "requires": [0], "tw": [null, null], "precedes": []}, "b616667c-47d3-4585-9eaa-87e056795e97": {"coords": [94, 25, 0], "duration": 119, "requires": [1], "tw": [null, null], "precedes": []}, "0263770a-ea2f-4874-88dd-dadfb2aaf297": {"coords": [136, 33, 0], "duration": 36, "requires": [1], "tw": [null, null], "precedes": []}, "c7d59065-5100-40a6-bc75-9c04ba33fb99": {"coords": [108, 1, 0], "duration": 67, "requires": [2], "tw": [null, null], "precedes": []}, "c8dcdef8-f55c-4ef2-9797-cb0a7c34e06b": {"coords": [122, 8, 0], "duration": 36, "requires": [1], "tw": [null, null], "precedes": []}, "b8fbf50e-2882-4307-82fc-5d4130bc5d30": {"coords": [41, 35, 0], "duration": 36, "requires": [0], "tw": [null, null], "precedes": []}, "1404fd00-8171-439a-84b4-c690394b900b": {"coords": [55, 26, 0], "duration": 67, "requires": [2], "tw": [null, null], "precedes": []}, "ba172acd-6bc8-4d11-ad0e-076b03c988af": {"coords": [70, 82, 0], "duration": 36, "requires": [0], "tw": [null, null], "precedes": []}, "dd6e2f16-9037-4bd0-b464-1d3263d79170": {"coords": [65, 57, 0], "duration": 119, "requires": [1], "tw": [null, null], "precedes": []}, "ec98c6de-6ca8-4278-8496-f6a7b8cf1b46": {"coords": [89, 96, 0], "duration": 36, "requires": [0], "tw": [null, null], "precedes": []}, "aa01b128-6c20-4ae9-864f-d15a25686c1a": {"coords": [81, 71, 0], "duration": 36, "requires": [0], "tw": [null, null], "precedes": []}, "10f62bca-7c1a-4ab9-bd94-56b22dd1e566": {"coords": [94, 65, 0], "duration": 119, "requires": [1], "tw": [null, null], "precedes": []}, "4bfed8c2-9838-4a5b-94fd-006c01e504aa": {"coords": [115, 69, 0], "duration": 36, "requires": [0], "tw": [null, null], "precedes": []}, "f586e38f-003e-48ad-9e6a-805debe80be4": {"coords": [92, 11, 0], "duration": 119, "requires": [0], "tw": [null, null], "precedes": []}, "2003b788-68dc-476a-95a4-b8b658211be1": {"coords": [149, 67, 0], "duration": 119, "requires": [1], "tw": [null, null], "precedes": []}, "73fa1e91-e2bc-4a0a-8bcf-c58c26d6c3c4": {"coords": [24, 34, 0], "duration": 119, "requires": [0], "tw": [null, null], "precedes": []}, "ca5948c6-c3a4-412a-8efa-09d6b715b0f0": {"coords": [51, 21, 0], "duration": 36, "requires": [1], "tw": [0, 1000000000000000], "precedes": [["15964fc1-b416-4801-9101-24f055ca7bdf", null, null, false]]}, "15964fc1-b416-4801-9101-24f055ca7bdf": {"coords": [48, 22, 0], "duration": 36, "requires": [1], "tw": [0, 1000000000000000], "precedes": [["0a09b582-451c-43f2-9a4c-4c3b51264df3", null, null, false]]}, "0a09b582-451c-43f2-9a4c-4c3b51264df3": {"coords": [63, 27, 0], "duration": 36, "requires": [0], "tw": [0, 1000000000000000], "precedes": [["7da36e52-ec83-4e7b-a158-c7ed006aa688", null, null, false]]}, "7da36e52-ec83-4e7b-a158-c7ed006aa688": {"coords": [47, 21, 0], "duration": 36, "requires": [0], "tw": [0, 1000000000000000], "precedes": [["3d2b4597-a644-47d7-92d2-440f8648eb2f", null, null, false]]}, "3d2b4597-a644-47d7-92d2-440f8648eb2f": {"coords": [57, 28, 0], "duration": 36, "requires": [0], "tw": [0, 1000000000000000], "precedes": [["23c5c0df-3861-45ce-af34-f82c094db7ec", null, null, false]]}, "23c5c0df-3861-45ce-af34-f82c094db7ec": {"coords": [58, 36, 0], "duration": 36, "requires": [0], "tw": [0, 1000000000000000], "precedes": [["dbb280f3-ceff-495b-bc72-a95eea8b5e06", null, null, false]]}, "dbb280f3-ceff-495b-bc72-a95eea8b5e06": {"coords": [74, 24, 0], "duration": 36, "requires": [0], "tw": [0, 1000000000000000], "precedes": [["65e52351-99b9-4255-afae-0252cc60be9e", null, null, false], ["96f0ec91-99c4-47b9-8aee-94d23e9bf676", null, null, false]]}, "65e52351-99b9-4255-afae-0252cc60be9e": {"coords": [63, 27, 0], "duration": 36, "requires": [0], "tw": [0, 1000000000000000], "precedes": []}, "96f0ec91-99c4-47b9-8aee-94d23e9bf676": {"coords": [85, 16, 0], "duration": 36, "requires": [0], "tw": [0, 1000000000000000], "precedes": []}}, "vehicles": {"0": {"speed": 2, "skills": [2]}, "1": {"speed": 1, "skills": [1]}, "2": {"speed": 2, "skills": [0]}, "3": {"speed": 2, "skills": [1]}, "4": {"speed": 2, "skills": [1]}, "5": {"speed": 2, "skills": [0]}, "6": {"speed": 1, "skills": [1]}, "7": {"speed": 1, "skills": [1]}, "8": {"speed": 2, "skills": [2]}, "9": {"speed": 2, "skills": [2]}}, "doc": "lol"}