{"nodes": {"9792ed8e-6656-409f-a0f6-40429ff44c9e": {"coords": [60, 60, 0], "duration": 0, "requires": [0], "tw": [null, null], "precedes": []}, "c0b58b70-75db-4934-be97-3d93552c6f6a": {"coords": [107, 92, 0], "duration": 66, "requires": [2], "tw": [null, null], "precedes": []}, "1d647a49-652f-48ba-9abd-0c61aad0f351": {"coords": [121, 63, 0], "duration": 66, "requires": [1], "tw": [null, null], "precedes": []}, "3cc8a4bf-171e-4442-a825-831facc1141d": {"coords": [0, 11, 0], "duration": 49, "requires": [0], "tw": [null, null], "precedes": []}, "9b769986-f593-472f-a6c7-8a6edbb372c8": {"coords": [139, 7, 0], "duration": 66, "requires": [0], "tw": [null, null], "precedes": []}, "c98e6daf-5341-44f7-8ad6-47d23e3e4000": {"coords": [139, 98, 0], "duration": 49, "requires": [0], "tw": [null, null], "precedes": []}, "983fcf11-5a97-44a6-9183-750db3d1fc79": {"coords": [79, 41, 0], "duration": 49, "requires": [2], "tw": [null, null], "precedes": []}, "cce73509-73ae-42da-9b04-4a353d54e1a0": {"coords": [4, 60, 0], "duration": 66, "requires": [1], "tw": [null, null], "precedes": []}, "e8acf244-b6d6-460c-ae77-6bfa12ba6044": {"coords": [4, 22, 0], "duration": 137, "requires": [1], "tw": [null, null], "precedes": []}, "6ddb8599-67d0-44fe-9709-05ca92ad124e": {"coords": [7, 2, 0], "duration": 137, "requires": [0], "tw": [null, null], "precedes": []}, "aa9d644d-639a-4683-8518-2f8783da228f": {"coords": [74, 94, 0], "duration": 137, "requires": [0], "tw": [null, null], "precedes": []}, "6308aa6e-a957-463e-aa51-567f6d150449": {"coords": [115, 33, 0], "duration": 66, "requires": [2], "tw": [null, null], "precedes": []}, "a95be23f-2d32-4172-9fda-15da10896657": {"coords": [89, 84, 0], "duration": 137, "requires": [2], "tw": [null, null], "precedes": []}, "a1993629-cd69-4ed0-8891-8df46de4e4d8": {"coords": [104, 18, 0], "duration": 66, "requires": [1], "tw": [null, null], "precedes": []}, "2a6b5833-3392-4e95-9526-caaef86d607f": {"coords": [28, 94, 0], "duration": 66, "requires": [1], "tw": [null, null], "precedes": []}, "acd6efbc-9d40-4cc4-91d2-ce32045d3585": {"coords": [74, 57, 0], "duration": 137, "requires": [2], "tw": [null, null], "precedes": []}, "975086df-a97e-48c6-828c-e4ac16d81eb2": {"coords": [20, 43, 0], "duration": 137, "requires": [2], "tw": [null, null], "precedes": []}, "7e3ae909-419a-437c-8361-2427ec613b51": {"coords": [67, 28, 0], "duration": 66, "requires": [0], "tw": [null, null], "precedes": []}, "7bd50033-3ad5-4a64-923a-250ff5a1ebf3": {"coords": [147, 93, 0], "duration": 66, "requires": [1], "tw": [null, null], "precedes": []}, "ca733181-11a9-4953-a697-cd5d7b67645d": {"coords": [9, 42, 0], "duration": 49, "requires": [2], "tw": [null, null], "precedes": []}, "550bf5a4-a634-4d2a-ba17-5931b693aed9": {"coords": [49, 94, 0], "duration": 137, "requires": [2], "tw": [null, null], "precedes": []}, "3dd50a71-32f8-4ce3-b8f3-062f855f2ff9": {"coords": [13, 82, 0], "duration": 137, "requires": [2], "tw": [null, null], "precedes": []}, "9b3893f4-15e6-4d6f-bb48-604ff9edd4fc": {"coords": [23, 92, 0], "duration": 66, "requires": [1], "tw": [null, null], "precedes": []}, "bac454ee-78ae-465f-ad78-278cc7e8fca5": {"coords": [18, 47, 0], "duration": 49, "requires": [0], "tw": [null, null], "precedes": []}, "c7185e8c-8278-44dd-a506-58b7cc66a333": {"coords": [46, 84, 0], "duration": 66, "requires": [2], "tw": [null, null], "precedes": []}, "8f9625c8-2037-4a49-a57a-9b7ba5af1d6a": {"coords": [72, 97, 0], "duration": 49, "requires": [1], "tw": [null, null], "precedes": []}, "edf5ac71-a7a6-4318-9172-219a248f0d7c": {"coords": [0, 0, 0], "duration": 137, "requires": [1], "tw": [null, null], "precedes": []}, "b5eff8a0-b209-4c2f-9710-5ad6bf6d74ee": {"coords": [45, 64, 0], "duration": 137, "requires": [1], "tw": [null, null], "precedes": []}, "0894338b-5652-4d70-ad62-bbd47e0af609": {"coords": [68, 74, 0], "duration": 49, "requires": [0], "tw": [null, null], "precedes": []}, "77821216-8564-4f6c-99c9-f3fcfda02e79": {"coords": [15, 94, 0], "duration": 137, "requires": [2], "tw": [null, null], "precedes": []}, "c2dd5a78-9b30-492d-bbe5-be41af9317ce": {"coords": [25, 84, 0], "duration": 137, "requires": [1], "tw": [null, null], "precedes": []}, "46f6a6b9-6bd2-4e48-95ab-456c0c86edeb": {"coords": [42, 19, 0], "duration": 66, "requires": [2], "tw": [null, null], "precedes": []}, "f854a1bc-202f-47d0-824b-c8fdbfa28ead": {"coords": [73, 18, 0], "duration": 66, "requires": [0], "tw": [null, null], "precedes": []}, "d6cdf544-0ece-496e-a9ca-ef5c9fbd3399": {"coords": [30, 10, 0], "duration": 137, "requires": [1], "tw": [null, null], "precedes": []}, "b0acd755-06ab-4290-a7bd-00d128c37f51": {"coords": [92, 77, 0], "duration": 49, "requires": [1], "tw": [null, null], "precedes": []}, "76947011-3cd3-4d95-869e-67a3033e4eb3": {"coords": [103, 19, 0], "duration": 49, "requires": [0], "tw": [null, null], "precedes": []}, "02d33af3-9b07-4195-8497-7a0ab268e763": {"coords": [31, 5, 0], "duration": 66, "requires": [0], "tw": [null, null], "precedes": []}, "8c146975-2616-41da-8d62-2269b1805a2d": {"coords": [102, 97, 0], "duration": 49, "requires": [0], "tw": [null, null], "precedes": []}, "2439ce59-d57f-4e4a-9bcc-6e228e43eb9c": {"coords": [118, 36, 0], "duration": 49, "requires": [1], "tw": [null, null], "precedes": []}, "9a8d9af7-50e8-440f-a0b1-fb98bf3a1cc2": {"coords": [81, 47, 0], "duration": 137, "requires": [2], "tw": [null, null], "precedes": []}, "b9d97821-f0c5-4837-aa57-b078240be588": {"coords": [147, 7, 0], "duration": 137, "requires": [0], "tw": [null, null], "precedes": []}, "b828c91f-3bbe-4685-8547-4d1438dc1629": {"coords": [34, 25, 0], "duration": 137, "requires": [0], "tw": [null, null], "precedes": []}, "49386aa3-a505-4448-b0ed-da00f4be20e7": {"coords": [131, 46, 0], "duration": 66, "requires": [1], "tw": [null, null], "precedes": []}, "bab60a99-a9cd-46f8-bb2e-21b2d7010766": {"coords": [103, 90, 0], "duration": 49, "requires": [2], "tw": [null, null], "precedes": []}, "3ea5f22e-0b22-4df6-aa3e-63c9ee95cf90": {"coords": [13, 75, 0], "duration": 137, "requires": [2], "tw": [null, null], "precedes": []}, "1950f062-8aa4-47f3-aa9f-3fa38a9b45e2": {"coords": [129, 95, 0], "duration": 49, "requires": [0], "tw": [null, null], "precedes": []}, "03eb9dc4-12bd-454e-8ad7-6299544dfe20": {"coords": [122, 9, 0], "duration": 49, "requires": [2], "tw": [null, null], "precedes": []}, "1bf5714c-fe79-42a8-8855-cd1ae16563aa": {"coords": [123, 59, 0], "duration": 49, "requires": [1], "tw": [null, null], "precedes": []}, "d5326995-80e0-4d10-a60a-c59404a78e9f": {"coords": [131, 55, 0], "duration": 66, "requires": [2], "tw": [null, null], "precedes": []}, "c89bb9c4-803f-4715-86fb-a175c2aa0c2a": {"coords": [43, 82, 0], "duration": 137, "requires": [1], "tw": [null, null], "precedes": []}, "637077d2-3dde-4e2b-b4ca-d4b3a989771d": {"coords": [33, 52, 0], "duration": 66, "requires": [0], "tw": [null, null], "precedes": []}, "80ae5d94-396e-42fd-ba3d-fffccdf89567": {"coords": [148, 72, 0], "duration": 66, "requires": [0], "tw": [null, null], "precedes": []}, "a9ddb9f8-836f-490d-b065-ec61b4ab3539": {"coords": [105, 9, 0], "duration": 137, "requires": [2], "tw": [null, null], "precedes": []}, "cb9e73f5-1b0c-420e-8e76-a755d8368cb1": {"coords": [21, 46, 0], "duration": 66, "requires": [1], "tw": [null, null], "precedes": []}, "0ff1f662-0bbf-4b1b-91bc-a98f599a3cde": {"coords": [108, 15, 0], "duration": 66, "requires": [1], "tw": [null, null], "precedes": []}, "4335a4de-f828-4e1c-a1aa-cdeea68128ef": {"coords": [45, 6, 0], "duration": 66, "requires": [1], "tw": [null, null], "precedes": []}, "9ad0aba9-d8bd-4118-b06c-b23ed7f3dbfb": {"coords": [46, 43, 0], "duration": 137, "requires": [1], "tw": [null, null], "precedes": []}, "9462e168-05d1-4c91-bc21-e3344de0e166": {"coords": [140, 93, 0], "duration": 49, "requires": [0], "tw": [null, null], "precedes": []}, "22f67814-cb14-437c-ac57-e0dc233d99fe": {"coords": [69, 93, 0], "duration": 66, "requires": [1], "tw": [null, null], "precedes": []}, "2c8eb852-7357-4ea7-88cb-d212cacb9152": {"coords": [128, 87, 0], "duration": 66, "requires": [0], "tw": [null, null], "precedes": []}, "6150b052-70ed-4eec-b4c1-892ad007055c": {"coords": [14, 49, 0], "duration": 137, "requires": [1], "tw": [null, null], "precedes": []}, "7cf2eb45-c1fa-4b2e-9abd-7e88fb4ceaae": {"coords": [69, 61, 0], "duration": 137, "requires": [2], "tw": [null, null], "precedes": []}, "b3ab7431-c651-444e-b337-816d1c106d32": {"coords": [94, 43, 0], "duration": 49, "requires": [0], "tw": [null, null], "precedes": []}, "b1508597-6412-4c3f-9b8f-3c6f49109343": {"coords": [48, 23, 0], "duration": 66, "requires": [2], "tw": [null, null], "precedes": []}, "865b61a8-7694-41cd-a54e-6557a2cea1b2": {"coords": [57, 62, 0], "duration": 49, "requires": [2], "tw": [null, null], "precedes": []}, "789a96d6-fe24-4bc1-a705-5a7c2bd18fe7": {"coords": [34, 28, 0], "duration": 49, "requires": [0], "tw": [null, null], "precedes": []}, "749ea2a3-32ed-4211-b2b1-506cf671270e": {"coords": [116, 32, 0], "duration": 49, "requires": [0], "tw": [null, null], "precedes": []}, "d78d4dbc-f6f3-4659-99b5-07797d5e1b5c": {"coords": [57, 9, 0], "duration": 66, "requires": [1], "tw": [null, null], "precedes": []}, "717db652-772b-4d51-b0bd-bc4dba5d1155": {"coords": [35, 67, 0], "duration": 137, "requires": [1], "tw": [null, null], "precedes": []}, "80e429d8-aabf-4184-a327-89e43cb7c971": {"coords": [109, 5, 0], "duration": 66, "requires": [1], "tw": [null, null], "precedes": []}, "af58e900-f14a-49df-89f3-6a57c88ec46d": {"coords": [92, 8, 0], "duration": 49, "requires": [2], "tw": [null, null], "precedes": []}, "f5090c92-5c99-40c9-994e-e5cafe83b5ec": {"coords": [118, 30, 0], "duration": 137, "requires": [2], "tw": [null, null], "precedes": []}, "271b4f31-8efb-421f-9d17-fe0e2b9581ed": {"coords": [54, 46, 0], "duration": 49, "requires": [2], "tw": [null, null], "precedes": []}, "8b97408c-3f2c-4136-b6f9-7c9845896024": {"coords": [33, 24, 0], "duration": 137, "requires": [0], "tw": [null, null], "precedes": []}, "247a9229-6f06-42c2-bb98-7fda5c485292": {"coords": [19, 7, 0], "duration": 66, "requires": [1], "tw": [null, null], "precedes": []}, "2910746c-f628-4643-89ca-47a0ee88c0b2": {"coords": [125, 55, 0], "duration": 137, "requires": [1], "tw": [null, null], "precedes": []}, "2b1cf0fb-42b6-43db-a643-28728c73cf89": {"coords": [97, 68, 0], "duration": 137, "requires": [2], "tw": [null, null], "precedes": []}, "048ce4ff-e501-46d7-9961-fe55c02ce7f3": {"coords": [130, 86, 0], "duration": 66, "requires": [0], "tw": [null, null], "precedes": []}, "d6da8382-a270-4fb5-b1a6-4fe9c0a6af05": {"coords": [51, 58, 0], "duration": 49, "requires": [0], "tw": [null, null], "precedes": []}, "ef75eaf3-0b71-4bd1-a6b3-3aa2a48c49b1": {"coords": [79, 32, 0], "duration": 137, "requires": [0], "tw": [null, null], "precedes": []}, "51930723-7cee-4562-b39f-7d319eecc487": {"coords": [35, 24, 0], "duration": 49, "requires": [1], "tw": [null, null], "precedes": []}, "561b12e6-217e-4ff5-8b74-fca9a7a1c681": {"coords": [69, 67, 0], "duration": 137, "requires": [1], "tw": [null, null], "precedes": []}, "6e85d8f3-3205-4cd1-923f-681e1954ea77": {"coords": [43, 22, 0], "duration": 49, "requires": [1], "tw": [null, null], "precedes": []}, "ded9fc72-a50c-4f82-8770-99e907ea8fc2": {"coords": [100, 89, 0], "duration": 66, "requires": [2], "tw": [null, null], "precedes": []}, "f5b34989-8c30-4285-b081-1eacf599a4ca": {"coords": [33, 81, 0], "duration": 66, "requires": [2], "tw": [null, null], "precedes": []}, "a44005ce-fe6d-4c9e-a34f-a91f37e56803": {"coords": [145, 90, 0], "duration": 66, "requires": [0], "tw": [null, null], "precedes": []}, "6a219967-b0c8-4936-965c-27121577bd8c": {"coords": [40, 73, 0], "duration": 49, "requires": [2], "tw": [null, null], "precedes": []}, "3d05a5c8-53d8-4dbf-b033-e6e97852dc1e": {"coords": [63, 40, 0], "duration": 49, "requires": [2], "tw": [null, null], "precedes": []}, "c9b7a1db-bcb1-40ca-a81b-f94157ac84eb": {"coords": [43, 36, 0], "duration": 66, "requires": [0], "tw": [0, 1000000000000000], "precedes": []}, "b6996be0-6588-45f1-bb85-64d6b52921d6": {"coords": [43, 36, 0], "duration": 49, "requires": [2], "tw": [0, 1000000000000000], "precedes": [["c9b7a1db-bcb1-40ca-a81b-f94157ac84eb", -49, -49, false]]}, "989a89ff-089c-48c5-83ca-b0a536fe3d29": {"coords": [42, 20, 0], "duration": 137, "requires": [1], "tw": [0, 1000000000000000], "precedes": []}, "8d4d463e-b587-4246-841a-858bdca593ce": {"coords": [42, 20, 0], "duration": 66, "requires": [1], "tw": [0, 1000000000000000], "precedes": [["989a89ff-089c-48c5-83ca-b0a536fe3d29", -66, -66, false]]}, "1322852d-4cd9-4930-a090-3ceb0198b256": {"coords": [146, 83, 0], "duration": 137, "requires": [1], "tw": [0, 1000000000000000], "precedes": []}, "95bcbc4d-fd35-4a42-9236-09d5ec4c8b33": {"coords": [146, 83, 0], "duration": 66, "requires": [1], "tw": [0, 1000000000000000], "precedes": [["1322852d-4cd9-4930-a090-3ceb0198b256", -66, -66, false]]}, "f6b70bbd-1c32-46ed-8557-8ba0d1dae9f8": {"coords": [53, 94, 0], "duration": 66, "requires": [2], "tw": [0, 1000000000000000], "precedes": []}, "1cb18a4d-8ea1-43d2-98e3-7646f320b107": {"coords": [53, 94, 0], "duration": 66, "requires": [1], "tw": [0, 1000000000000000], "precedes": [["f6b70bbd-1c32-46ed-8557-8ba0d1dae9f8", -66, -66, false]]}, "ce340e74-e564-4aae-98e4-79d92be4c319": {"coords": [92, 86, 0], "duration": 66, "requires": [0], "tw": [0, 1000000000000000], "precedes": []}, "990323b0-4e93-42f5-8c7a-2060ad124c7e": {"coords": [92, 86, 0], "duration": 137, "requires": [2], "tw": [0, 1000000000000000], "precedes": [["ce340e74-e564-4aae-98e4-79d92be4c319", -137, -137, false]]}, "8d022e09-f9d3-419a-b269-c8ac12d5cef3": {"coords": [144, 57, 0], "duration": 137, "requires": [2], "tw": [0, 1000000000000000], "precedes": []}, "599fa8e7-c1b7-42e2-a159-c75ac4d21c20": {"coords": [144, 57, 0], "duration": 137, "requires": [1], "tw": [0, 1000000000000000], "precedes": [["8d022e09-f9d3-419a-b269-c8ac12d5cef3", -137, -137, false]]}, "c12fe254-caff-4b61-9ca0-d7ed3617d2bc": {"coords": [12, 56, 0], "duration": 49, "requires": [0], "tw": [0, 1000000000000000], "precedes": []}, "a6c58cf2-e6cb-49ac-a307-322cd15cfe47": {"coords": [12, 56, 0], "duration": 49, "requires": [0], "tw": [0, 1000000000000000], "precedes": [["c12fe254-caff-4b61-9ca0-d7ed3617d2bc", -49, -49, false]]}, "240b43e3-6a6b-41db-a530-2e3b6b9cd0ea": {"coords": [30, 35, 0], "duration": 66, "requires": [0], "tw": [0, 1000000000000000], "precedes": []}, "be92098e-6eb4-44ff-ba3a-4c563104b709": {"coords": [30, 35, 0], "duration": 66, "requires": [0], "tw": [0, 1000000000000000], "precedes": [["240b43e3-6a6b-41db-a530-2e3b6b9cd0ea", -66, -66, false]]}, "3bba07e8-7eff-4e1c-bec4-f39accd5f740": {"coords": [114, 91, 0], "duration": 137, "requires": [0], "tw": [0, 1000000000000000], "precedes": []}, "147a9998-2ce1-4c56-8dd1-9ba278e88912": {"coords": [114, 91, 0], "duration": 49, "requires": [0], "tw": [0, 1000000000000000], "precedes": [["3bba07e8-7eff-4e1c-bec4-f39accd5f740", -49, -49, false]]}, "b5321e06-521e-405e-a2c4-151cc44700cf": {"coords": [55, 97, 0], "duration": 66, "requires": [0], "tw": [0, 1000000000000000], "precedes": []}, "51c9784a-b0b2-44e4-9e80-493d3af11b1d": {"coords": [55, 97, 0], "duration": 66, "requires": [0], "tw": [0, 1000000000000000], "precedes": [["b5321e06-521e-405e-a2c4-151cc44700cf", -66, -66, false]]}, "32042ab6-f82b-4406-9ef5-613596ba53bb": {"coords": [52, 99, 0], "duration": 66, "requires": [0], "tw": [0, 1000000000000000], "precedes": []}, "8363d713-8bad-4265-b2bd-5f39f6f2694e": {"coords": [52, 99, 0], "duration": 137, "requires": [0], "tw": [0, 1000000000000000], "precedes": [["32042ab6-f82b-4406-9ef5-613596ba53bb", -137, -137, false]]}, "2040267e-7ec8-44cf-b15d-eb8cddcdcd70": {"coords": [134, 39, 0], "duration": 49, "requires": [0], "tw": [0, 1000000000000000], "precedes": []}, "6d4f2649-1c35-4c00-ad3d-1c462adf457c": {"coords": [134, 39, 0], "duration": 137, "requires": [0], "tw": [0, 1000000000000000], "precedes": [["2040267e-7ec8-44cf-b15d-eb8cddcdcd70", -137, -137, false]]}, "3715c2f9-cd65-46a9-b17f-1cad76362c01": {"coords": [65, 34, 0], "duration": 66, "requires": [0], "tw": [0, 1000000000000000], "precedes": []}, "dc06b07d-31cf-4f4b-9a00-de2714c2e9f2": {"coords": [65, 34, 0], "duration": 49, "requires": [0], "tw": [0, 1000000000000000], "precedes": [["3715c2f9-cd65-46a9-b17f-1cad76362c01", -49, -49, false]]}}, "vehicles": {"0": {"speed": 1, "skills": [2]}, "1": {"speed": 1, "skills": [2]}, "2": {"speed": 1, "skills": [2]}, "3": {"speed": 2, "skills": [0]}, "4": {"speed": 2, "skills": [0]}, "5": {"speed": 1, "skills": [1]}, "6": {"speed": 1, "skills": [2]}, "7": {"speed": 2, "skills": [1]}, "8": {"speed": 2, "skills": [0]}, "9": {"speed": 1, "skills": [0, 1]}}, "doc": "lol"}